xuefei/__init__.py
xuefei/print_xuefei.py
xuefei-0.0.2.dist-info/LICENSE
xuefei-0.0.2.dist-info/METADATA
xuefei-0.0.2.dist-info/WHEEL
xuefei-0.0.2.dist-info/top_level.txt
xuefei-0.0.2.dist-info/RECORD
