Metadata-Version: 2.1
Name: xuefei
Version: 0.0.2
Summary: 别觉得自己厉害
Home-page: https://www.baidu.com
Author: xuefei
Author-email: 494199078@qq.com
Classifier: Programming Language :: Python :: 3
Classifier: License :: OSI Approved :: MIT License
Classifier: Operating System :: OS Independent
License-File: LICENSE
